clu/__init__.py
clu/asynclib.py
clu/asynclib_test.py
clu/checkpoint.py
clu/checkpoint_test.py
clu/deterministic_data.py
clu/deterministic_data_test.py
clu/metrics.py
clu/metrics_test.py
clu/parameter_overview.py
clu/parameter_overview_test.py
clu/periodic_actions.py
clu/periodic_actions_test.py
clu/preprocess_spec.py
clu/preprocess_spec_test.py
clu/profiler.py
clu/values.py
clu/data/__init__.py
clu/data/dataset_iterator.py
clu/data/dataset_iterator_test.py
clu/internal/__init__.py
clu/internal/utils.py
clu/internal/utils_test.py
clu/metric_writers/__init__.py
clu/metric_writers/async_writer.py
clu/metric_writers/async_writer_test.py
clu/metric_writers/interface.py
clu/metric_writers/logging_writer.py
clu/metric_writers/logging_writer_test.py
clu/metric_writers/multi_writer.py
clu/metric_writers/multi_writer_test.py
clu/metric_writers/summary_writer.py
clu/metric_writers/torch_tensorboard_writer.py
clu/metric_writers/torch_tensorboard_writer_test.py
clu/metric_writers/utils.py
clu/metric_writers/utils_test.py
clu/metric_writers/tf/__init__.py
clu/metric_writers/tf/summary_writer.py
clu/metric_writers/tf/summary_writer_test.py
clu/platform/__init__.py
clu/platform/interface.py
clu/platform/local.py
clu-0.0.12.dist-info/AUTHORS
clu-0.0.12.dist-info/LICENSE
clu-0.0.12.dist-info/METADATA
clu-0.0.12.dist-info/WHEEL
clu-0.0.12.dist-info/top_level.txt
clu-0.0.12.dist-info/RECORD
