Metadata-Version: 2.1
Name: clu
Version: 0.0.12
Summary: Set of libraries for ML training loops in JAX.
Home-page: http://github.com/google/CommonLoopUtils
Author: Common Loop Utils Authors
Author-email: no-reply@google.com
License: Apache 2.0
Keywords: JAX machine learning
Classifier: Development Status :: 4 - Beta
Classifier: Intended Audience :: Developers
Classifier: Intended Audience :: Science/Research
Classifier: License :: OSI Approved :: Apache Software License
Classifier: Programming Language :: Python
Classifier: Topic :: Scientific/Engineering :: Artificial Intelligence
License-File: LICENSE
License-File: AUTHORS
Requires-Dist: absl-py
Requires-Dist: etils[epath]
Requires-Dist: flax
Requires-Dist: jax
Requires-Dist: jaxlib
Requires-Dist: ml-collections
Requires-Dist: numpy
Requires-Dist: packaging
Requires-Dist: typing-extensions
Requires-Dist: wrapt
Provides-Extra: test
Requires-Dist: pytest ; extra == 'test'
Requires-Dist: tensorflow ; extra == 'test'
Requires-Dist: tensorflow-datasets ; extra == 'test'
Requires-Dist: torch >=2.0.0 ; extra == 'test'
